surflink/__init__.py
surflink/document.py
surflink/exception.py
surflink/extract.py
surflink/highlevel.py
surflink-0.0.2.dist-info/LICENSE
surflink-0.0.2.dist-info/METADATA
surflink-0.0.2.dist-info/WHEEL
surflink-0.0.2.dist-info/top_level.txt
surflink-0.0.2.dist-info/RECORD
