Metadata-Version: 2.1
Name: surflink
Version: 0.0.2
Summary: Extracts links/urls from html markup with ability to choose which urls to be extracted.
Home-page: https://github.com/sekgobela-kevin/surflink
Author: Sekgobela Kevin
Author-email: kevinnoko23@gmail.com
Project-URL: Bug Tracker, https://github.com/sekgobela-kevin/surflink/issues
Keywords: extract,webpage,html,link,url
Classifier: Intended Audience :: Developers
Classifier: Development Status :: 2 - Pre-Alpha
Classifier: Programming Language :: Python
Classifier: Programming Language :: Python :: 3
Classifier: Natural Language :: English
Classifier: Topic :: Software Development :: Libraries
Classifier: Topic :: Software Development :: Libraries :: Python Modules
Classifier: Topic :: Text Processing :: Markup :: HTML
Classifier: Topic :: Text Processing :: Markup :: XML
Classifier: Topic :: Utilities
Requires-Python: >=3.6
License-File: LICENSE
Requires-Dist: bs4
Requires-Dist: resid (<1.0.0)
